wordlistools/__init__.py
wordlistools/__main__.py
wordlistools/api.py
wordlistools/base.py
wordlistools/cmdline.py
wordlistools/consts.py
wordlistools/helpertest.py
wordlistools/parsers.py
wordlistools/plugins.py
wordlistools/plugins/__init__.py
wordlistools/plugins/filters_tools.py
wordlistools/plugins/modifiers_tools.py
wordlistools/plugins/plugins.py
wordlistools/plugins/statistics_tools.py
wordlistools-0.1.10.dist-info/LICENSE
wordlistools-0.1.10.dist-info/METADATA
wordlistools-0.1.10.dist-info/WHEEL
wordlistools-0.1.10.dist-info/entry_points.txt
wordlistools-0.1.10.dist-info/top_level.txt
wordlistools-0.1.10.dist-info/RECORD
